simpletype/__init__.py
simpletype/_version.py
simpletype/api.py
simpletype/constants.py
simpletype/paths.py
simpletype/schema.py
simpletype/sentinel.py
simpletype/typehint.py
simpletype/docs/__init__.py
simpletype/tests/__init__.py
simpletype/tests/helper.py
simpletype/vendor/__init__.py
simpletype/vendor/pytest_cov_helper.py
simpletype-0.2.6.dist-info/AUTHORS.rst
simpletype-0.2.6.dist-info/LICENSE.txt
simpletype-0.2.6.dist-info/METADATA
simpletype-0.2.6.dist-info/WHEEL
simpletype-0.2.6.dist-info/top_level.txt
simpletype-0.2.6.dist-info/RECORD
